odoo/addons/carrier_environment/README.rst
odoo/addons/carrier_environment/__init__.py
odoo/addons/carrier_environment/__manifest__.py
odoo/addons/carrier_environment/i18n/carrier_environment.pot
odoo/addons/carrier_environment/models/__init__.py
odoo/addons/carrier_environment/models/carrier_account.py
odoo/addons/carrier_environment/readme/CONFIGURE.rst
odoo/addons/carrier_environment/readme/CONTRIBUTORS.rst
odoo/addons/carrier_environment/readme/DESCRIPTION.rst
odoo/addons/carrier_environment/readme/USAGE.rst
odoo/addons/carrier_environment/static/description/icon.png
odoo/addons/carrier_environment/static/description/index.html
odoo12_addon_carrier_environment-12.0.1.0.1.dist-info/METADATA
odoo12_addon_carrier_environment-12.0.1.0.1.dist-info/WHEEL
odoo12_addon_carrier_environment-12.0.1.0.1.dist-info/top_level.txt
odoo12_addon_carrier_environment-12.0.1.0.1.dist-info/RECORD
